JCDock/__init__.py
JCDock/Examples/run_test_suite.py
JCDock/Examples/simple_examples/__init__.py
JCDock/Examples/simple_examples/basic_containers.py
JCDock/Examples/simple_examples/icon_demo.py
JCDock/Examples/simple_examples/main_window_with_menu.py
JCDock/Examples/simple_examples/parameterized_widget_demo.py
JCDock/Examples/simple_examples/save_load_demo.py
JCDock/Examples/simple_examples/toolbar_enhanced_demo.py
JCDock/Examples/test_suite/__init__.py
JCDock/Examples/test_suite/app.py
JCDock/Examples/test_suite/main.py
JCDock/Examples/test_suite/managers/__init__.py
JCDock/Examples/test_suite/managers/layout_manager.py
JCDock/Examples/test_suite/managers/test_manager.py
JCDock/Examples/test_suite/managers/ui_manager.py
JCDock/Examples/test_suite/utils/__init__.py
JCDock/Examples/test_suite/utils/constants.py
JCDock/Examples/test_suite/utils/data_generator.py
JCDock/Examples/test_suite/utils/test_utilities.py
JCDock/Examples/test_suite/widgets/__init__.py
JCDock/Examples/test_suite/widgets/financial_widgets.py
JCDock/Examples/test_suite/widgets/test_widgets.py
JCDock/core/__init__.py
JCDock/core/docking_manager.py
JCDock/core/docking_state.py
JCDock/core/widget_registry.py
JCDock/factories/__init__.py
JCDock/factories/model_update_engine.py
JCDock/factories/widget_factory.py
JCDock/factories/window_manager.py
JCDock/interaction/__init__.py
JCDock/interaction/docking_overlay.py
JCDock/interaction/drag_drop_controller.py
JCDock/interaction/drag_proxy.py
JCDock/interaction/overlay_manager.py
JCDock/interaction/tab_drag_preview.py
JCDock/model/__init__.py
JCDock/model/dock_model.py
JCDock/model/layout_renderer.py
JCDock/model/layout_serializer.py
JCDock/utils/__init__.py
JCDock/utils/hit_test_cache.py
JCDock/utils/icon_cache.py
JCDock/utils/performance_monitor.py
JCDock/utils/resize_cache.py
JCDock/utils/resize_gesture_manager.py
JCDock/utils/resize_throttler.py
JCDock/utils/windows_shadow.py
JCDock/widgets/__init__.py
JCDock/widgets/dock_container.py
jcdock-1.1.0.dist-info/licenses/LICENSE
jcdock-1.1.0.dist-info/METADATA
jcdock-1.1.0.dist-info/WHEEL
jcdock-1.1.0.dist-info/top_level.txt
jcdock-1.1.0.dist-info/RECORD
