Metadata-Version: 2.4
Name: JCDock
Version: 1.1.0
Summary: A flexible and customizable docking framework for PySide6 applications.
Author-email: Justin Cook <jcook5376@gmail.com>
License: MIT License
Project-URL: Homepage, https://github.com/JustiSoft/JCDock
Project-URL: Repository, https://github.com/JustiSoft/JCDock
Project-URL: Issues, https://github.com/JustiSoft/JCDock/issues
Project-URL: Documentation, https://github.com/JustiSoft/JCDock#readme
Keywords: pyside,qt,docking,gui,widget
Classifier: Development Status :: 5 - Production/Stable
Classifier: Intended Audience :: Developers
Classifier: License :: OSI Approved :: MIT License
Classifier: Operating System :: OS Independent
Classifier: Programming Language :: Python :: 3
Classifier: Programming Language :: Python :: 3.9
Classifier: Programming Language :: Python :: 3.10
Classifier: Programming Language :: Python :: 3.11
Classifier: Programming Language :: Python :: 3.12
Classifier: Programming Language :: Python :: 3.13
Classifier: Topic :: Software Development :: User Interfaces
Classifier: Topic :: Software Development :: Libraries :: Python Modules
License-File: LICENSE
Requires-Dist: PySide6<7.0.0,>=6.5.0
Dynamic: license-file
